TwrpBuilder
