Metadata-Version: 1.0
Name: TwrpBuilder
Version: 0.9
Summary: Wrapper for building Twrp
Home-page: UNKNOWN
Author: Android Lover
Author-email: androidlover5842@gmail.com
License: MIT
Keywords: Twrp Root Android
Platform: UNKNOWN
